{
  "playerSpeed": 100,
  "platformScale": 3,
  "projectileDuration": 5000,
  "platforms": [
    {
      "x": 100,
      "y": 100,
      "numTiles": 6,
      "key": "PLATFORM"
    },
    {
      "x": 250,
      "y": 250,
      "numTiles": 8,
      "key": "PLATFORM"
    },
    {
      "x": 150,
      "y": 410,
      "numTiles": 8,
      "key": "PLATFORM"
    },
    {
      "x": 42,
      "y": 536,
      "numTiles": 16,
      "key": "GROUND"
    }
  ],
  "tiledDecoration": [
    {
      "x": 250,
      "y": 280,
      "numTilesWide": 6,
      "numTilesHigh": 3,
      "key": "UNDERPASS"
    },
    {
      "x": 96,
      "y": 560,
      "numTilesWide": 15,
      "numTilesHigh": 1,
      "key": "UNDERGROUND"
    }
  ],
  "start": {
    "x": 300,
    "y": 180
  },
  "finish": {
    "x": 600,
    "y": 500
  },
  "monsters": {
    "squids": [
      {
        "x1": 700,
        "y1": 300,
        "x2": 600,
        "y2": 100,
        "duration": 1000
      },
      {
        "x1": 50,
        "y1": 250,
        "x2": 220,
        "y2": 250,
        "duration": 1000
      }
    ],
    "fanatics": [
      {
        "y": 400,
        "x1": 200,
        "x2": 700
      }
    ]
  },
  "traps" : [
    {
      "x": 400,
      "y": 395,
      "onTime":  2000,
      "offTime": 2000
    }
  ],
  "decorations": [
    {
      "x": 700,
      "y": 520,
      "key": "TOMBSTONE"
    },
    {
      "x": 357,
      "y": 500,
      "key": "TREE"
    }
  ]

}